basic_colors.py
basic_colors-0.1.1.dist-info/METADATA
basic_colors-0.1.1.dist-info/WHEEL
basic_colors-0.1.1.dist-info/top_level.txt
basic_colors-0.1.1.dist-info/RECORD
