Metadata-Version: 2.2
Name: basic-colors
Version: 0.1.1
Summary: A module for printing colored text to the terminal
Home-page: https://github.com/elPytel/basic-colors
Author: elPytel
Author-email: jaroslav.korner1@gmail.com
Classifier: Programming Language :: Python :: 3
Classifier: License :: OSI Approved :: MIT License
Classifier: Operating System :: OS Independent
Requires-Python: >=3.6
Dynamic: author
Dynamic: author-email
Dynamic: classifier
Dynamic: description
Dynamic: description-content-type
Dynamic: home-page
Dynamic: requires-python
Dynamic: summary
